DESCRIPTION
MANIFEST.in
README
VERSION
setup.py
mus/__init__.py
mus/cli.py
mus/mongo.py
mus.egg-info/PKG-INFO
mus.egg-info/SOURCES.txt
mus.egg-info/dependency_links.txt
mus.egg-info/entry_points.txt
mus.egg-info/requires.txt
mus.egg-info/top_level.txt
mus/etc/_mus.config
mus/etc/_yak.config
mus/etc/plugin.config
mus/plugin/__init__.py
mus/plugin/base.py