Metadata-Version: 1.1
Name: mus
Version: 0.0.4
Summary: Mus - light weight distributed logging
Home-page: https://encrypted.google.com/#q=mus&safe=off
Author: Mark Fiers
Author-email: mark.fiers.42@gmail.com
License: UNKNOWN
Platform: UNKNOWN
Classifier: Development Status :: 4 - Beta
Classifier: Environment :: Console
Classifier: Operating System :: OS Independent
Classifier: Programming Language :: Python
Classifier: Programming Language :: Python :: 3
Classifier: Programming Language :: Python :: 3.3
Classifier: Programming Language :: Python :: 3.4
